package_version_present.py
package_version_present-0.0.3.dist-info/LICENSE
package_version_present-0.0.3.dist-info/METADATA
package_version_present-0.0.3.dist-info/WHEEL
package_version_present-0.0.3.dist-info/entry_points.txt
package_version_present-0.0.3.dist-info/top_level.txt
package_version_present-0.0.3.dist-info/RECORD
